glacis/__init__.py
glacis/__main__.py
glacis/client.py
glacis/crypto.py
glacis/models.py
glacis/storage.py
glacis/streaming.py
glacis/wasm_runtime.py
glacis/integrations/__init__.py
glacis/integrations/anthropic.py
glacis/integrations/openai.py
glacis/wasm/s3p_core_wasi.wasm
glacis-0.1.4.dist-info/METADATA
glacis-0.1.4.dist-info/WHEEL
glacis-0.1.4.dist-info/licenses/LICENSE
glacis-0.1.4.dist-info/RECORD
